eo_lookup.py
eo_lookup-0.1.0.dist-info/DESCRIPTION.rst
eo_lookup-0.1.0.dist-info/LICENSE.txt
eo_lookup-0.1.0.dist-info/METADATA
eo_lookup-0.1.0.dist-info/RECORD
eo_lookup-0.1.0.dist-info/WHEEL
eo_lookup-0.1.0.dist-info/metadata.json
eo_lookup-0.1.0.dist-info/top_level.txt
