Metadata-Version: 2.0
Name: eo-lookup
Version: 0.1.0
Summary: Esperanto dictionary lookup tool
Home-page: https://github.com/open-esperanto/eo-lookup
Author: Open Esperanto
Author-email: admin@libraro.net
License: UNKNOWN
Keywords: esperanto
Platform: UNKNOWN
Classifier: Development Status :: 4 - Beta
Classifier: Intended Audience :: Developers
Classifier: License :: OSI Approved :: MIT License
Classifier: Programming Language :: Python :: 3
